neuro_low_light/__init__.py
neuro_low_light/inference.py
neuro_low_light/model.py
neuro_low_light/utils.py
neuro_low_light/weights/best_model.pth
neuro_low_light-0.1.0.dist-info/licenses/LICENSE
neuro_low_light-0.1.0.dist-info/METADATA
neuro_low_light-0.1.0.dist-info/WHEEL
neuro_low_light-0.1.0.dist-info/entry_points.txt
neuro_low_light-0.1.0.dist-info/top_level.txt
neuro_low_light-0.1.0.dist-info/RECORD
