Metadata-Version: 2.4
Name: neuro-low-light
Version: 0.1.0
Summary: Professional low-light image enhancement using Zero-DCE++
Home-page: https://github.com/Parshva2605/neuro-low-light
Author: Parshva Shah
Author-email: Parshva Shah <shahparshva2005@gmail.com>
License: MIT
Project-URL: Homepage, https://github.com/Parshva2605/neuro-low-light
Project-URL: Repository, https://github.com/Parshva2605/neuro-low-light
Project-URL: Issues, https://github.com/Parshva2605/neuro-low-light/issues
Classifier: Development Status :: 4 - Beta
Classifier: Intended Audience :: Developers
Classifier: Intended Audience :: Science/Research
Classifier: License :: OSI Approved :: MIT License
Classifier: Programming Language :: Python :: 3
Classifier: Programming Language :: Python :: 3.9
Classifier: Programming Language :: Python :: 3.10
Classifier: Programming Language :: Python :: 3.11
Classifier: Topic :: Scientific/Engineering :: Artificial Intelligence
Classifier: Topic :: Scientific/Engineering :: Image Processing
Requires-Python: >=3.9
License-File: LICENSE
Requires-Dist: torch>=2.0.0
Requires-Dist: torchvision>=0.15.0
Requires-Dist: opencv-python>=4.5.0
Requires-Dist: numpy>=1.21.0
Requires-Dist: pillow>=9.0.0
Requires-Dist: tqdm>=4.60.0
Dynamic: author
Dynamic: home-page
Dynamic: license-file
Dynamic: requires-python
